{
	"id": "0zlv2YXyrkByJRC",
	"json": "{\"id\":\"0zlv2YXyrkByJRC\",\"url\":\"https://123movies.sc/watch-gregorys-girl-1980-123movies.html\",\"uniqueKey\":\"https://123movies.sc/watch-gregorys-girl-1980-123movies.html\",\"method\":\"GET\",\"noRetry\":false,\"retryCount\":0,\"errorMessages\":[],\"headers\":{},\"userData\":{}}",
	"method": "GET",
	"orderNo": 1677170151182,
	"retryCount": 0,
	"uniqueKey": "https://123movies.sc/watch-gregorys-girl-1980-123movies.html",
	"url": "https://123movies.sc/watch-gregorys-girl-1980-123movies.html"
}