{
	"id": "2StYpC5W2c2kyku",
	"json": "{\"id\":\"2StYpC5W2c2kyku\",\"url\":\"https://123movies.sc/star/ruben-castellon-perez.html\",\"uniqueKey\":\"https://123movies.sc/star/ruben-castellon-perez.html\",\"method\":\"GET\",\"noRetry\":false,\"retryCount\":0,\"errorMessages\":[],\"headers\":{},\"userData\":{}}",
	"method": "GET",
	"orderNo": 1677170195679,
	"retryCount": 0,
	"uniqueKey": "https://123movies.sc/star/ruben-castellon-perez.html",
	"url": "https://123movies.sc/star/ruben-castellon-perez.html"
}