{
	"id": "5TvyvsZU8VJZunk",
	"json": "{\"id\":\"5TvyvsZU8VJZunk\",\"url\":\"https://123movies.sc/star/michael-patrick-denis.html\",\"uniqueKey\":\"https://123movies.sc/star/michael-patrick-denis.html\",\"method\":\"GET\",\"noRetry\":false,\"retryCount\":0,\"errorMessages\":[],\"headers\":{},\"userData\":{}}",
	"method": "GET",
	"orderNo": 1677170216902,
	"retryCount": 0,
	"uniqueKey": "https://123movies.sc/star/michael-patrick-denis.html",
	"url": "https://123movies.sc/star/michael-patrick-denis.html"
}