{
	"id": "5z02zYPcVziR3jp",
	"json": "{\"id\":\"5z02zYPcVziR3jp\",\"url\":\"https://123movies.sc/genres/biography.html?p=2\",\"loadedUrl\":\"https://123movies.sc/genres/biography.html?p=2\",\"uniqueKey\":\"https://123movies.sc/genres/biography.html?p=2\",\"method\":\"GET\",\"noRetry\":false,\"retryCount\":0,\"errorMessages\":[],\"headers\":{},\"userData\":{\"__crawlee\":{\"state\":4}},\"handledAt\":\"2023-02-23T16:35:49.161Z\"}",
	"method": "GET",
	"orderNo": null,
	"retryCount": 0,
	"uniqueKey": "https://123movies.sc/genres/biography.html?p=2",
	"url": "https://123movies.sc/genres/biography.html?p=2"
}