{
	"id": "7Be3SMyhVOob3Th",
	"json": "{\"id\":\"7Be3SMyhVOob3Th\",\"url\":\"https://123movies.sc/star/devon-coull.html\",\"loadedUrl\":\"https://123movies.sc/star/devon-coull.html\",\"uniqueKey\":\"https://123movies.sc/star/devon-coull.html\",\"method\":\"GET\",\"noRetry\":false,\"retryCount\":0,\"errorMessages\":[],\"headers\":{},\"userData\":{\"__crawlee\":{\"state\":4}},\"handledAt\":\"2023-02-23T16:36:16.898Z\"}",
	"method": "GET",
	"orderNo": null,
	"retryCount": 0,
	"uniqueKey": "https://123movies.sc/star/devon-coull.html",
	"url": "https://123movies.sc/star/devon-coull.html"
}