{
	"id": "9XrJhNvV8s3DGF0",
	"json": "{\"id\":\"9XrJhNvV8s3DGF0\",\"url\":\"https://123movies.sc/star/bridgette-wilson-sampras.html\",\"uniqueKey\":\"https://123movies.sc/star/bridgette-wilson-sampras.html\",\"method\":\"GET\",\"noRetry\":false,\"retryCount\":0,\"errorMessages\":[],\"headers\":{},\"userData\":{}}",
	"method": "GET",
	"orderNo": 1677170150479,
	"retryCount": 0,
	"uniqueKey": "https://123movies.sc/star/bridgette-wilson-sampras.html",
	"url": "https://123movies.sc/star/bridgette-wilson-sampras.html"
}