{
	"id": "BJyCbU2ODlVMQRW",
	"json": "{\"id\":\"BJyCbU2ODlVMQRW\",\"url\":\"https://123movies.sc/star/panuvat-anthony-nanakornpanom.html\",\"uniqueKey\":\"https://123movies.sc/star/panuvat-anthony-nanakornpanom.html\",\"method\":\"GET\",\"noRetry\":false,\"retryCount\":0,\"errorMessages\":[],\"headers\":{},\"userData\":{}}",
	"method": "GET",
	"orderNo": 1677170191040,
	"retryCount": 0,
	"uniqueKey": "https://123movies.sc/star/panuvat-anthony-nanakornpanom.html",
	"url": "https://123movies.sc/star/panuvat-anthony-nanakornpanom.html"
}