{
	"id": "brOwM2PSpYVE8ey",
	"json": "{\"id\":\"brOwM2PSpYVE8ey\",\"url\":\"https://123movies.sc/star/kadrolsha-ona-carole.html\",\"loadedUrl\":\"https://123movies.sc/star/kadrolsha-ona-carole.html\",\"uniqueKey\":\"https://123movies.sc/star/kadrolsha-ona-carole.html\",\"method\":\"GET\",\"noRetry\":false,\"retryCount\":0,\"errorMessages\":[],\"headers\":{},\"userData\":{\"__crawlee\":{\"state\":4}},\"handledAt\":\"2023-02-23T16:36:29.943Z\"}",
	"method": "GET",
	"orderNo": null,
	"retryCount": 0,
	"uniqueKey": "https://123movies.sc/star/kadrolsha-ona-carole.html",
	"url": "https://123movies.sc/star/kadrolsha-ona-carole.html"
}