{
	"id": "Cysa1reIfw95dA6",
	"json": "{\"id\":\"Cysa1reIfw95dA6\",\"url\":\"https://123movies.sc/star/forrest-kiyoshi-hoffman.html\",\"uniqueKey\":\"https://123movies.sc/star/forrest-kiyoshi-hoffman.html\",\"method\":\"GET\",\"noRetry\":false,\"retryCount\":0,\"errorMessages\":[],\"headers\":{},\"userData\":{}}",
	"method": "GET",
	"orderNo": 1677170172575,
	"retryCount": 0,
	"uniqueKey": "https://123movies.sc/star/forrest-kiyoshi-hoffman.html",
	"url": "https://123movies.sc/star/forrest-kiyoshi-hoffman.html"
}