{
	"id": "diL8oMmiWEU7QeV",
	"json": "{\"id\":\"diL8oMmiWEU7QeV\",\"url\":\"https://123movies.sc/star/genesis-castro-diaz.html\",\"uniqueKey\":\"https://123movies.sc/star/genesis-castro-diaz.html\",\"method\":\"GET\",\"noRetry\":false,\"retryCount\":0,\"errorMessages\":[],\"headers\":{},\"userData\":{}}",
	"method": "GET",
	"orderNo": 1677170216634,
	"retryCount": 0,
	"uniqueKey": "https://123movies.sc/star/genesis-castro-diaz.html",
	"url": "https://123movies.sc/star/genesis-castro-diaz.html"
}