{
	"id": "GN96OKTu9wftH13",
	"json": "{\"id\":\"GN96OKTu9wftH13\",\"url\":\"https://123movies.sc/star/clarence-gilyard-jr.html\",\"uniqueKey\":\"https://123movies.sc/star/clarence-gilyard-jr.html\",\"method\":\"GET\",\"noRetry\":false,\"retryCount\":0,\"errorMessages\":[],\"headers\":{},\"userData\":{}}",
	"method": "GET",
	"orderNo": 1677170165720,
	"retryCount": 0,
	"uniqueKey": "https://123movies.sc/star/clarence-gilyard-jr.html",
	"url": "https://123movies.sc/star/clarence-gilyard-jr.html"
}