{
	"id": "h9UK29YA3xDolRq",
	"json": "{\"id\":\"h9UK29YA3xDolRq\",\"url\":\"https://123movies.sc/watch-vantage-point-2008-123movies.html\",\"uniqueKey\":\"https://123movies.sc/watch-vantage-point-2008-123movies.html\",\"method\":\"GET\",\"noRetry\":false,\"retryCount\":0,\"errorMessages\":[],\"headers\":{},\"userData\":{}}",
	"method": "GET",
	"orderNo": 1677170134217,
	"retryCount": 0,
	"uniqueKey": "https://123movies.sc/watch-vantage-point-2008-123movies.html",
	"url": "https://123movies.sc/watch-vantage-point-2008-123movies.html"
}