{
	"id": "jMAYQpRqd7UW0Md",
	"json": "{\"id\":\"jMAYQpRqd7UW0Md\",\"url\":\"https://123movies.sc/star/sara-carolynn-kennedy.html\",\"uniqueKey\":\"https://123movies.sc/star/sara-carolynn-kennedy.html\",\"method\":\"GET\",\"noRetry\":false,\"retryCount\":0,\"errorMessages\":[],\"headers\":{},\"userData\":{}}",
	"method": "GET",
	"orderNo": 1677170188422,
	"retryCount": 0,
	"uniqueKey": "https://123movies.sc/star/sara-carolynn-kennedy.html",
	"url": "https://123movies.sc/star/sara-carolynn-kennedy.html"
}