{
	"id": "JvUkm5DwS8ptir5",
	"json": "{\"id\":\"JvUkm5DwS8ptir5\",\"url\":\"https://123movies.sc/star/james-hiroyuki-liao.html\",\"uniqueKey\":\"https://123movies.sc/star/james-hiroyuki-liao.html\",\"method\":\"GET\",\"noRetry\":false,\"retryCount\":0,\"errorMessages\":[],\"headers\":{},\"userData\":{}}",
	"method": "GET",
	"orderNo": 1677170157395,
	"retryCount": 0,
	"uniqueKey": "https://123movies.sc/star/james-hiroyuki-liao.html",
	"url": "https://123movies.sc/star/james-hiroyuki-liao.html"
}