{
	"id": "LoQxK0UZxhNMoJM",
	"json": "{\"id\":\"LoQxK0UZxhNMoJM\",\"url\":\"https://123movies.sc/watch-camera-store-2017-123movies.html\",\"uniqueKey\":\"https://123movies.sc/watch-camera-store-2017-123movies.html\",\"method\":\"GET\",\"noRetry\":false,\"retryCount\":0,\"errorMessages\":[],\"headers\":{},\"userData\":{}}",
	"method": "GET",
	"orderNo": 1677170217939,
	"retryCount": 0,
	"uniqueKey": "https://123movies.sc/watch-camera-store-2017-123movies.html",
	"url": "https://123movies.sc/watch-camera-store-2017-123movies.html"
}