{
	"id": "nE2fappoyZ7Y4RO",
	"json": "{\"id\":\"nE2fappoyZ7Y4RO\",\"url\":\"https://123movies.sc/star/idriss-abdillahi-houfaneh.html\",\"uniqueKey\":\"https://123movies.sc/star/idriss-abdillahi-houfaneh.html\",\"method\":\"GET\",\"noRetry\":false,\"retryCount\":0,\"errorMessages\":[],\"headers\":{},\"userData\":{}}",
	"method": "GET",
	"orderNo": 1677170157822,
	"retryCount": 0,
	"uniqueKey": "https://123movies.sc/star/idriss-abdillahi-houfaneh.html",
	"url": "https://123movies.sc/star/idriss-abdillahi-houfaneh.html"
}