{
	"id": "okMomT1s9fVIlcV",
	"json": "{\"id\":\"okMomT1s9fVIlcV\",\"url\":\"https://123movies.sc/star/katie-alexander-thom.html\",\"uniqueKey\":\"https://123movies.sc/star/katie-alexander-thom.html\",\"method\":\"GET\",\"noRetry\":false,\"retryCount\":0,\"errorMessages\":[],\"headers\":{},\"userData\":{}}",
	"method": "GET",
	"orderNo": 1677170209567,
	"retryCount": 0,
	"uniqueKey": "https://123movies.sc/star/katie-alexander-thom.html",
	"url": "https://123movies.sc/star/katie-alexander-thom.html"
}