{
	"id": "omWeT2unH53VwjZ",
	"json": "{\"id\":\"omWeT2unH53VwjZ\",\"url\":\"https://123movies.sc/star/april-hernandez-castillo.html\",\"uniqueKey\":\"https://123movies.sc/star/april-hernandez-castillo.html\",\"method\":\"GET\",\"noRetry\":false,\"retryCount\":0,\"errorMessages\":[],\"headers\":{},\"userData\":{}}",
	"method": "GET",
	"orderNo": 1677170128047,
	"retryCount": 0,
	"uniqueKey": "https://123movies.sc/star/april-hernandez-castillo.html",
	"url": "https://123movies.sc/star/april-hernandez-castillo.html"
}