{
	"id": "raZ5aCZpWsH2twl",
	"json": "{\"id\":\"raZ5aCZpWsH2twl\",\"url\":\"https://123movies.sc/star/michael-schlingmann.html\",\"uniqueKey\":\"https://123movies.sc/star/michael-schlingmann.html\",\"method\":\"GET\",\"noRetry\":false,\"retryCount\":0,\"errorMessages\":[],\"headers\":{},\"userData\":{}}",
	"method": "GET",
	"orderNo": 1677170214416,
	"retryCount": 0,
	"uniqueKey": "https://123movies.sc/star/michael-schlingmann.html",
	"url": "https://123movies.sc/star/michael-schlingmann.html"
}