{
	"id": "sq7S86KdFVVk7d5",
	"json": "{\"id\":\"sq7S86KdFVVk7d5\",\"url\":\"https://123movies.sc/star/elizabeth-weinstein.html\",\"uniqueKey\":\"https://123movies.sc/star/elizabeth-weinstein.html\",\"method\":\"GET\",\"noRetry\":false,\"retryCount\":0,\"errorMessages\":[],\"headers\":{},\"userData\":{}}",
	"method": "GET",
	"orderNo": 1677170173320,
	"retryCount": 0,
	"uniqueKey": "https://123movies.sc/star/elizabeth-weinstein.html",
	"url": "https://123movies.sc/star/elizabeth-weinstein.html"
}