{
	"id": "sRAt8QtjJlKDdWg",
	"json": "{\"id\":\"sRAt8QtjJlKDdWg\",\"url\":\"https://123movies.sc/star/louise-lemoine-torres.html\",\"uniqueKey\":\"https://123movies.sc/star/louise-lemoine-torres.html\",\"method\":\"GET\",\"noRetry\":false,\"retryCount\":0,\"errorMessages\":[],\"headers\":{},\"userData\":{}}",
	"method": "GET",
	"orderNo": 1677170205649,
	"retryCount": 0,
	"uniqueKey": "https://123movies.sc/star/louise-lemoine-torres.html",
	"url": "https://123movies.sc/star/louise-lemoine-torres.html"
}