{
	"id": "sx4lYnACUnoTxSC",
	"json": "{\"id\":\"sx4lYnACUnoTxSC\",\"url\":\"https://123movies.sc/star/christopher-halsted.html\",\"uniqueKey\":\"https://123movies.sc/star/christopher-halsted.html\",\"method\":\"GET\",\"noRetry\":false,\"retryCount\":0,\"errorMessages\":[],\"headers\":{},\"userData\":{}}",
	"method": "GET",
	"orderNo": 1677170195436,
	"retryCount": 0,
	"uniqueKey": "https://123movies.sc/star/christopher-halsted.html",
	"url": "https://123movies.sc/star/christopher-halsted.html"
}