{
	"id": "uAgtI5CaSMPq7Z9",
	"json": "{\"id\":\"uAgtI5CaSMPq7Z9\",\"url\":\"https://123movies.sc/star/lielle-tova-blinkoff.html\",\"uniqueKey\":\"https://123movies.sc/star/lielle-tova-blinkoff.html\",\"method\":\"GET\",\"noRetry\":false,\"retryCount\":0,\"errorMessages\":[],\"headers\":{},\"userData\":{}}",
	"method": "GET",
	"orderNo": 1677170135159,
	"retryCount": 0,
	"uniqueKey": "https://123movies.sc/star/lielle-tova-blinkoff.html",
	"url": "https://123movies.sc/star/lielle-tova-blinkoff.html"
}