{
	"id": "UTPgjduz5lXK3rX",
	"json": "{\"id\":\"UTPgjduz5lXK3rX\",\"url\":\"https://123movies.sc/star/magdalena-gnatowska.html\",\"uniqueKey\":\"https://123movies.sc/star/magdalena-gnatowska.html\",\"method\":\"GET\",\"noRetry\":false,\"retryCount\":0,\"errorMessages\":[],\"headers\":{},\"userData\":{}}",
	"method": "GET",
	"orderNo": 1677170157559,
	"retryCount": 0,
	"uniqueKey": "https://123movies.sc/star/magdalena-gnatowska.html",
	"url": "https://123movies.sc/star/magdalena-gnatowska.html"
}