{
	"id": "vqpL1DJIy7TcmhE",
	"json": "{\"id\":\"vqpL1DJIy7TcmhE\",\"url\":\"https://123movies.sc/watch-last-seen-alive-2022-123movies.html\",\"uniqueKey\":\"https://123movies.sc/watch-last-seen-alive-2022-123movies.html\",\"method\":\"GET\",\"noRetry\":false,\"retryCount\":0,\"errorMessages\":[],\"headers\":{},\"userData\":{}}",
	"method": "GET",
	"orderNo": 1677170174308,
	"retryCount": 0,
	"uniqueKey": "https://123movies.sc/watch-last-seen-alive-2022-123movies.html",
	"url": "https://123movies.sc/watch-last-seen-alive-2022-123movies.html"
}