{
	"id": "VRrm62pkRh4etj9",
	"json": "{\"id\":\"VRrm62pkRh4etj9\",\"url\":\"https://123movies.sc/star/stacy-clausen.html\",\"loadedUrl\":\"https://123movies.sc/star/stacy-clausen.html\",\"uniqueKey\":\"https://123movies.sc/star/stacy-clausen.html\",\"method\":\"GET\",\"noRetry\":false,\"retryCount\":0,\"errorMessages\":[],\"headers\":{},\"userData\":{\"__crawlee\":{\"state\":4}},\"handledAt\":\"2023-02-23T16:36:31.231Z\"}",
	"method": "GET",
	"orderNo": null,
	"retryCount": 0,
	"uniqueKey": "https://123movies.sc/star/stacy-clausen.html",
	"url": "https://123movies.sc/star/stacy-clausen.html"
}