{
	"id": "w99LwA4Cj7FUetO",
	"json": "{\"id\":\"w99LwA4Cj7FUetO\",\"url\":\"https://123movies.sc/star/francis-m-curnutte-iii.html\",\"uniqueKey\":\"https://123movies.sc/star/francis-m-curnutte-iii.html\",\"method\":\"GET\",\"noRetry\":false,\"retryCount\":0,\"errorMessages\":[],\"headers\":{},\"userData\":{}}",
	"method": "GET",
	"orderNo": 1677170148892,
	"retryCount": 0,
	"uniqueKey": "https://123movies.sc/star/francis-m-curnutte-iii.html",
	"url": "https://123movies.sc/star/francis-m-curnutte-iii.html"
}