{
	"id": "WezHYem86492rC3",
	"json": "{\"id\":\"WezHYem86492rC3\",\"url\":\"https://123movies.sc/star/natalie-garcia-fryman.html\",\"uniqueKey\":\"https://123movies.sc/star/natalie-garcia-fryman.html\",\"method\":\"GET\",\"noRetry\":false,\"retryCount\":0,\"errorMessages\":[],\"headers\":{},\"userData\":{}}",
	"method": "GET",
	"orderNo": 1677170116896,
	"retryCount": 0,
	"uniqueKey": "https://123movies.sc/star/natalie-garcia-fryman.html",
	"url": "https://123movies.sc/star/natalie-garcia-fryman.html"
}