{
	"id": "xwlvWesovMCm1S5",
	"json": "{\"id\":\"xwlvWesovMCm1S5\",\"url\":\"https://123movies.sc/watch-8mm-1999-123movies.html\",\"uniqueKey\":\"https://123movies.sc/watch-8mm-1999-123movies.html\",\"method\":\"GET\",\"noRetry\":false,\"retryCount\":0,\"errorMessages\":[],\"headers\":{},\"userData\":{}}",
	"method": "GET",
	"orderNo": 1677170140005,
	"retryCount": 0,
	"uniqueKey": "https://123movies.sc/watch-8mm-1999-123movies.html",
	"url": "https://123movies.sc/watch-8mm-1999-123movies.html"
}