{
	"id": "zcFLBEdSiluyWBu",
	"json": "{\"id\":\"zcFLBEdSiluyWBu\",\"url\":\"https://123movies.sc/star/christopher-collins.html\",\"uniqueKey\":\"https://123movies.sc/star/christopher-collins.html\",\"method\":\"GET\",\"noRetry\":false,\"retryCount\":0,\"errorMessages\":[],\"headers\":{},\"userData\":{}}",
	"method": "GET",
	"orderNo": 1677170153942,
	"retryCount": 0,
	"uniqueKey": "https://123movies.sc/star/christopher-collins.html",
	"url": "https://123movies.sc/star/christopher-collins.html"
}