{
	"id": "zTVf4heTCIrZN3U",
	"json": "{\"id\":\"zTVf4heTCIrZN3U\",\"url\":\"https://123movies.sc/star/brent-huff.html\",\"loadedUrl\":\"https://123movies.sc/star/brent-huff.html\",\"uniqueKey\":\"https://123movies.sc/star/brent-huff.html\",\"method\":\"GET\",\"noRetry\":false,\"retryCount\":0,\"errorMessages\":[],\"headers\":{},\"userData\":{\"__crawlee\":{\"state\":4}},\"handledAt\":\"2023-02-23T16:36:36.853Z\"}",
	"method": "GET",
	"orderNo": null,
	"retryCount": 0,
	"uniqueKey": "https://123movies.sc/star/brent-huff.html",
	"url": "https://123movies.sc/star/brent-huff.html"
}